gunbot_sdk/__init__.py
gunbot_sdk/api_client.py
gunbot_sdk/configuration.py
gunbot_sdk/rest.py
gunbot_sdk/api/__init__.py
gunbot_sdk/api/gunbot_api.py
gunbot_sdk/models/__init__.py
gunbot_sdk/models/asset_total_item.py
gunbot_sdk/models/assets_total_request.py
gunbot_sdk/models/assets_total_response.py
gunbot_sdk/models/auth_status_response.py
gunbot_sdk/models/balance_item.py
gunbot_sdk/models/balances_response.py
gunbot_sdk/models/chart_data_request.py
gunbot_sdk/models/chart_data_response.py
gunbot_sdk/models/chart_mark_item.py
gunbot_sdk/models/chart_marks_response.py
gunbot_sdk/models/config_full_response.py
gunbot_sdk/models/config_pair_add_request.py
gunbot_sdk/models/config_pair_remove_request.py
gunbot_sdk/models/config_strategy_add_request.py
gunbot_sdk/models/config_strategy_remove_request.py
gunbot_sdk/models/config_update_request.py
gunbot_sdk/models/config_update_response.py
gunbot_sdk/models/core_mem_raw_request.py
gunbot_sdk/models/core_mem_raw_response.py
gunbot_sdk/models/core_mem_single_request.py
gunbot_sdk/models/core_mem_snapshot_response.py
gunbot_sdk/models/error_response.py
gunbot_sdk/models/file_aclar_content_response.py
gunbot_sdk/models/file_content_response.py
gunbot_sdk/models/file_get_request.py
gunbot_sdk/models/file_list_response.py
gunbot_sdk/models/file_state_content_response.py
gunbot_sdk/models/file_strategy_write_request.py
gunbot_sdk/models/file_write_request.py
gunbot_sdk/models/gunbot_config.py
gunbot_sdk/models/license_keys_edit_request.py
gunbot_sdk/models/login_request.py
gunbot_sdk/models/login_response.py
gunbot_sdk/models/market_candles_response.py
gunbot_sdk/models/market_orderbook_data.py
gunbot_sdk/models/market_orderbook_response.py
gunbot_sdk/models/ohlcv_data.py
gunbot_sdk/models/one_of_file_write_request_document.py
gunbot_sdk/models/one_of_order_item_id.py
gunbot_sdk/models/order_item.py
gunbot_sdk/models/orderbook_level.py
gunbot_sdk/models/orders_day_response.py
gunbot_sdk/models/orders_page_multi_response.py
gunbot_sdk_python-0.1.0.dist-info/licenses/LICENSE
gunbot_sdk_python-0.1.0.dist-info/METADATA
gunbot_sdk_python-0.1.0.dist-info/WHEEL
gunbot_sdk_python-0.1.0.dist-info/top_level.txt
gunbot_sdk_python-0.1.0.dist-info/RECORD
