Metadata-Version: 2.4
Name: gunbot-sdk-python
Version: 0.1.0
Summary: Official Gunbot SDK for Python
Author-email: Gunbot <support@gunbot.freshdesk.com>
License-Expression: MIT
Project-URL: Homepage, https://www.gunbot.com
Project-URL: Source, https://github.com/gunthardeniro/gunbot-sdk-python
Project-URL: Tracker, https://github.com/gunthardeniro/gunbot-sdk-python/issues
Keywords: gunbot,python,sdk,api,crypto-trading,trading-bot,automated-trading,stocks,etf
Classifier: Development Status :: 4 - Beta
Classifier: Programming Language :: Python :: 3 :: Only
Classifier: Programming Language :: Python :: 3.9
Classifier: Programming Language :: Python :: 3.10
Classifier: Programming Language :: Python :: 3.11
Classifier: Programming Language :: Python :: 3.12
Classifier: Typing :: Typed
Requires-Python: >=3.9
License-File: LICENSE
Requires-Dist: urllib3>=1.26
Requires-Dist: six>=1.16
Requires-Dist: certifi>=2023.7
Requires-Dist: python-dateutil>=2.9
Dynamic: license-file
